lzttest/__init__.py
lzttest/lzttest.py
lzttest-1.0.0.dist-info/METADATA
lzttest-1.0.0.dist-info/WHEEL
lzttest-1.0.0.dist-info/top_level.txt
lzttest-1.0.0.dist-info/RECORD
