Metadata-Version: 2.1
Name: lzttest
Version: 1.0.0
Summary: Something
Home-page: https://github.com/Infqq/simpledemotivators
Author: your_nickname
Author-email: UNKNOWN
License: UNKNOWN
Platform: UNKNOWN
Classifier: Programming Language :: Python :: 3.6
Classifier: Programming Language :: Python :: 3.7
Classifier: Operating System :: OS Independent
